htmltagparse/__init__.py
htmltagparse/build.py
htmltagparse/cleaner.py
htmltagparse/exceptions.py
htmltagparse/html_tags.py
htmltagparse/parser.py
htmltagparse-3.1.dist-info/LICENSE
htmltagparse-3.1.dist-info/METADATA
htmltagparse-3.1.dist-info/WHEEL
htmltagparse-3.1.dist-info/top_level.txt
htmltagparse-3.1.dist-info/RECORD
