Metadata-Version: 2.1
Name: htmltagparse
Version: 3.1
Summary: A tool designed to quickly parse html tags and elements.
Home-page: https://github.com/xyzpw/htmltagparse/
Author: xyzpw
Maintainer: xyzpw
License: MIT
Classifier: Programming Language :: Python :: 3
Classifier: Programming Language :: Python :: 3.10
Classifier: Programming Language :: Python :: 3.11
Classifier: Topic :: Text Processing :: Markup
Classifier: Topic :: Text Processing :: Markup :: HTML
Classifier: Topic :: Utilities
Classifier: License :: OSI Approved :: MIT License
Classifier: Operating System :: POSIX :: Linux
Classifier: Intended Audience :: Developers
Requires-Python: >=3.10
License-File: LICENSE
Requires-Dist: beautifulsoup4 ==4.*
Requires-Dist: requests ==2.*
Requires-Dist: html5lib ==1.*
